{
  "2026-04-16": {
    "url": "https://www.criterionchannel.com/tos",
    "scraped_at": "2026-04-16T15:31:06.546141",
    "content_length": 0,
    "changed": false,
    "content": ""
  },
  "2026-04-17": {
    "url": "https://www.criterionchannel.com/tos",
    "scraped_at": "2026-04-17T09:00:39.687753",
    "content_length": 0,
    "changed": false,
    "content": ""
  },
  "2026-04-20": {
    "url": "https://www.criterionchannel.com/tos",
    "scraped_at": "2026-04-20T10:33:49.975547",
    "content_length": 0,
    "changed": false,
    "content": ""
  }
}